ppvector/__init__.py
ppvector/predict.py
ppvector/trainer.py
ppvector/configs/augmentation.yml
ppvector/configs/cam++.yml
ppvector/configs/ecapa_tdnn.yml
ppvector/configs/eres2net.yml
ppvector/configs/res2net.yml
ppvector/configs/resnet_se.yml
ppvector/configs/tdnn.yml
ppvector/data_utils/__init__.py
ppvector/data_utils/collate_fn.py
ppvector/data_utils/featurizer.py
ppvector/data_utils/pk_sampler.py
ppvector/data_utils/reader.py
ppvector/infer_utils/__init__.py
ppvector/infer_utils/player.py
ppvector/infer_utils/speaker_diarization.py
ppvector/infer_utils/viewer.py
ppvector/loss/__init__.py
ppvector/loss/aamloss.py
ppvector/loss/amloss.py
ppvector/loss/armloss.py
ppvector/loss/celoss.py
ppvector/loss/sphereface2.py
ppvector/loss/subcenterloss.py
ppvector/loss/tripletangularmarginloss.py
ppvector/metric/__init__.py
ppvector/metric/metrics.py
ppvector/models/__init__.py
ppvector/models/campplus.py
ppvector/models/ecapa_tdnn.py
ppvector/models/eres2net.py
ppvector/models/fc.py
ppvector/models/pooling.py
ppvector/models/res2net.py
ppvector/models/resnet_se.py
ppvector/models/tdnn.py
ppvector/models/utils.py
ppvector/optimizer/__init__.py
ppvector/optimizer/scheduler.py
ppvector/utils/__init__.py
ppvector/utils/checkpoint.py
ppvector/utils/record.py
ppvector/utils/utils.py
ppvector-1.1.5.dist-info/LICENSE
ppvector-1.1.5.dist-info/METADATA
ppvector-1.1.5.dist-info/WHEEL
ppvector-1.1.5.dist-info/top_level.txt
ppvector-1.1.5.dist-info/RECORD
